tdseird/Model.py
tdseird/US_Model.py
tdseird/__init__.py
tdseird-0.0.2.dist-info/LICENSE
tdseird-0.0.2.dist-info/METADATA
tdseird-0.0.2.dist-info/WHEEL
tdseird-0.0.2.dist-info/top_level.txt
tdseird-0.0.2.dist-info/RECORD
